{
  "listen": "127.0.0.1:8067",
  "database": "ircthing.db",
  "user": {
    "username": "AlteredParadox",
    "password_hash": "<output of: ircd-web -hash-password>"
  },
  "networks": [
    {
      "name": "libera",
      "addr": "irc.libera.chat:6697",
      "tls": true,
      "nick": "mynick",
      "realname": "My Name",
      "sasl": {
        "mechanism": "",
        "login": "mynick",
        "password": "my-nickserv-password"
      },
      "channels": ["#go-nuts", "#linux"]
    },
    {
      "name": "selfhosted-example",
      "addr": "irc.example.org:6697",
      "tls": true,
      "proxy": "socks5://127.0.0.1:9050",
      "trusted_fingerprints": [
        "<sha256 hex of the server's certificate, for self-signed servers>"
      ],
      "nick": "mynick",
      "sasl": {
        "mechanism": "EXTERNAL",
        "cert_file": "/etc/ircthing/client-cert.pem",
        "key_file": "/etc/ircthing/client-key.pem"
      },
      "channels": ["#home"]
    }
  ],
  "session_ttl_days": 30
}
